README.md
setup.py
pyDAOE.egg-info/PKG-INFO
pyDAOE.egg-info/SOURCES.txt
pyDAOE.egg-info/dependency_links.txt
pyDAOE.egg-info/requires.txt
pyDAOE.egg-info/top_level.txt
pydaoe/__init__.py
pydaoe/anova.py
pydaoe/generate_design.py
pydaoe/simple_comparative.py
pydaoe/utils.py
tests/__init__.py
tests/test_chap2.py
tests/test_chap3.py
tests/test_chap4.py
tests/test_chap5.py
tests/test_chap6.py
tests/test_generate.py
tests/test_utils.py