Metadata-Version: 2.1
Name: pyDAOE
Version: 0.1.0
Summary: Design and Analysis of Experiments
Home-page: https://github.com/danieleongari/pyDAOE
Author: Daniele Ongari
Author-email: daniele.ongari@gmail.com
License: Creative Commons
Platform: UNKNOWN
Classifier: Programming Language :: Python
Provides-Extra: testing
Provides-Extra: pre-commit
